ylearn-0.2.0.dist-info/WHEEL
ylearn-0.2.0.dist-info/top_level.txt
ylearn-0.2.0.dist-info/LICENSE
ylearn-0.2.0.dist-info/RECORD
ylearn-0.2.0.dist-info/METADATA
ylearn/_version.py
ylearn/__init__.py
ylearn/utils/_common.py
ylearn/utils/logging.py
ylearn/utils/__init__.py
ylearn/policy/policy_model.py
ylearn/policy/__init__.py
ylearn/policy/_tree/tree_criterion.cpp
ylearn/policy/_tree/__init__.py
ylearn/policy/_tree/tree_criterion.pyx
ylearn/policy/_tree/tree_criterion.cpython-310-x86_64-linux-gnu.so
ylearn/policy/_tree/tree_criterion.pxd
ylearn/stats_inference/__init__.py
ylearn/api/_identifier.py
ylearn/api/_wrapper.py
ylearn/api/utils.py
ylearn/api/smoke.py
ylearn/api/__init__.py
ylearn/api/_why.py
ylearn/estimator_model/base_models.py
ylearn/estimator_model/causal_forest.py
ylearn/estimator_model/propensity_score.py
ylearn/estimator_model/_nn.py
ylearn/estimator_model/utils.py
ylearn/estimator_model/_permuted.py
ylearn/estimator_model/effect_score.py
ylearn/estimator_model/meta_learner.py
ylearn/estimator_model/approximation_bound.py
ylearn/estimator_model/deepiv.py
ylearn/estimator_model/doubly_robust.py
ylearn/estimator_model/ensemble.py
ylearn/estimator_model/iv.py
ylearn/estimator_model/causal_tree.py
ylearn/estimator_model/_factory.py
ylearn/estimator_model/double_ml.py
ylearn/estimator_model/__init__.py
ylearn/estimator_model/_generalized_forest/_grf.py
ylearn/estimator_model/_generalized_forest/__init__.py
ylearn/estimator_model/_generalized_forest/_base_forest.py
ylearn/estimator_model/_generalized_forest/tree/_criterion.cpp
ylearn/estimator_model/_generalized_forest/tree/_grf_tree.py
ylearn/estimator_model/_generalized_forest/tree/_util_lib.cpp
ylearn/estimator_model/_generalized_forest/tree/_util.cpp
ylearn/estimator_model/_generalized_forest/tree/_util.pyx
ylearn/estimator_model/_generalized_forest/tree/_splitter.cpython-310-x86_64-linux-gnu.so
ylearn/estimator_model/_generalized_forest/tree/_tree.pxd
ylearn/estimator_model/_generalized_forest/tree/_tree.cpp
ylearn/estimator_model/_generalized_forest/tree/_util.pxd
