Metadata-Version: 2.1
Name: ylearn
Version: 0.2.0
Summary: A python package for causal inference
Home-page: https://github.com/DataCanvasIO/YLearn
Author: DataCanvas Community
Author-email: yangjian@zetyun.com
License: Apache License 2.0
Classifier: Operating System :: OS Independent
Classifier: Intended Audience :: Developers
Classifier: Intended Audience :: Education
Classifier: Intended Audience :: Science/Research
Classifier: Programming Language :: Python
Classifier: Programming Language :: Python :: 3.6
Classifier: Programming Language :: Python :: 3.7
Classifier: Programming Language :: Python :: 3.8
Classifier: Programming Language :: Python :: 3.9
Classifier: Programming Language :: Python :: 3.10
Classifier: Topic :: Scientific/Engineering
Classifier: Topic :: Scientific/Engineering :: Artificial Intelligence
Classifier: Topic :: Software Development
Classifier: Topic :: Software Development :: Libraries
Classifier: Topic :: Software Development :: Libraries :: Python Modules
Requires-Python: >=3.6.*
License-File: LICENSE
Requires-Dist: numpy (>=1.16.5)
Requires-Dist: pandas (>=0.25.3)
Requires-Dist: scikit-learn (>=0.22.1)
Requires-Dist: scipy
Requires-Dist: networkx
Requires-Dist: ipython
Requires-Dist: torch
Requires-Dist: joblib
Requires-Dist: pydot
Requires-Dist: tqdm
Provides-Extra: all
Requires-Dist: ipywidgets ; extra == 'all'
Requires-Dist: jupyterlab ; extra == 'all'
Requires-Dist: jupyterlab-widgets ; extra == 'all'
Requires-Dist: matplotlib ; extra == 'all'
Requires-Dist: shap ; extra == 'all'
Requires-Dist: tqdm ; extra == 'all'
Provides-Extra: notebook
Requires-Dist: jupyterlab ; extra == 'notebook'
Requires-Dist: ipywidgets ; extra == 'notebook'
Requires-Dist: jupyterlab-widgets ; extra == 'notebook'
Requires-Dist: matplotlib ; extra == 'notebook'
Requires-Dist: tqdm ; extra == 'notebook'
Requires-Dist: shap ; extra == 'notebook'
